{
  "main": {
    "id": "09beda985f54e1ae",
    "type": "split",
    "children": [
      {
        "id": "f747d91caa184cfc",
        "type": "tabs",
        "children": [
          {
            "id": "e57cac18db5576fc",
            "type": "leaf",
            "state": {
              "type": "markdown",
              "state": {
                "file": "Diane Enns.md",
                "mode": "source",
                "source": false
              },
              "icon": "lucide-file",
              "title": "Diane Enns"
            }
          }
        ]
      }
    ],
    "direction": "vertical"
  },
  "left": {
    "id": "ab160983b0b9249d",
    "type": "split",
    "children": [
      {
        "id": "c34addea73636b6c",
        "type": "tabs",
        "children": [
          {
            "id": "b810d69d14f6cfab",
            "type": "leaf",
            "state": {
              "type": "file-explorer",
              "state": {
                "sortOrder": "alphabetical",
                "autoReveal": false
              },
              "icon": "lucide-folder-closed",
              "title": "Files"
            }
          },
          {
            "id": "2f23917ba6532366",
            "type": "leaf",
            "state": {
              "type": "search",
              "state": {
                "query": "",
                "matchingCase": false,
                "explainSearch": false,
                "collapseAll": false,
                "extraContext": false,
                "sortOrder": "alphabetical"
              },
              "icon": "lucide-search",
              "title": "Search"
            }
          },
          {
            "id": "726853f10b7def12",
            "type": "leaf",
            "state": {
              "type": "bookmarks",
              "state": {},
              "icon": "lucide-bookmark",
              "title": "Bookmarks"
            }
          }
        ]
      }
    ],
    "direction": "horizontal",
    "width": 300
  },
  "right": {
    "id": "62be838bcc12c394",
    "type": "split",
    "children": [
      {
        "id": "39f3877944d6a780",
        "type": "tabs",
        "children": [
          {
            "id": "af5f5bfc855bb29d",
            "type": "leaf",
            "state": {
              "type": "backlink",
              "state": {
                "file": "Term Paper.md",
                "collapseAll": false,
                "extraContext": false,
                "sortOrder": "alphabetical",
                "showSearch": false,
                "searchQuery": "",
                "backlinkCollapsed": false,
                "unlinkedCollapsed": true
              },
              "icon": "links-coming-in",
              "title": "Backlinks for Term Paper"
            }
          },
          {
            "id": "986241a12ca041bf",
            "type": "leaf",
            "state": {
              "type": "outgoing-link",
              "state": {
                "file": "MS2/Slides/HannahArendtLectureIdeologyTerror.pdf",
                "linksCollapsed": false,
                "unlinkedCollapsed": true
              },
              "icon": "links-going-out",
              "title": "Outgoing links from HannahArendtLectureIdeologyTerror"
            }
          },
          {
            "id": "aca679c97cd91a7e",
            "type": "leaf",
            "state": {
              "type": "tag",
              "state": {
                "sortOrder": "frequency",
                "useHierarchy": true,
                "showSearch": false,
                "searchQuery": ""
              },
              "icon": "lucide-tags",
              "title": "Tags"
            }
          },
          {
            "id": "a096faa561aea0b6",
            "type": "leaf",
            "state": {
              "type": "all-properties",
              "state": {
                "sortOrder": "frequency",
                "showSearch": false,
                "searchQuery": ""
              },
              "icon": "lucide-archive",
              "title": "All properties"
            }
          },
          {
            "id": "0752de3a3f11f24e",
            "type": "leaf",
            "state": {
              "type": "outline",
              "state": {
                "file": "MS2/Slides/HannahArendtLectureIdeologyTerror.pdf",
                "followCursor": false,
                "showSearch": false,
                "searchQuery": ""
              },
              "icon": "lucide-list",
              "title": "Outline of HannahArendtLectureIdeologyTerror"
            }
          }
        ]
      }
    ],
    "direction": "horizontal",
    "width": 331.5,
    "collapsed": true
  },
  "left-ribbon": {
    "hiddenItems": {
      "switcher:Open quick switcher": false,
      "graph:Open graph view": false,
      "canvas:Create new canvas": false,
      "daily-notes:Open today's daily note": false,
      "templates:Insert template": false,
      "command-palette:Open command palette": false,
      "bases:Create new base": false,
      "obsidian-git:Open Git source control": false
    }
  },
  "active": "e57cac18db5576fc",
  "lastOpenFiles": [
    "Mijuskovic.md",
    "Ratcliffe and Strawson.md",
    "Roberts & Krueger.md",
    "Seeman.md",
    "MS2/Jennifer Gaffney - Political Loneliness Modern Liberal Subjects in Hiding (2020, Rowman Littlefield) - libgen.li.pdf",
    "MS2/Hannah Arendt - The Origins of Totalitarianism (1973, Harcourt, Brace, Jovanovich) - libgen.li-505-524.pdf",
    "MS2/Slides/DEnnsOrganized Loneliness.pdf",
    "MS1/The Southern J of Philosophy - 2020 - Roberts - Loneliness and the Emotional Experience of Absence.pdf",
    "MS2/Term Paper/OL_TermPaper_ref.pdf",
    "MS2/Term Paper/MS22068_OL_TERMPAPER.pdf",
    "MS2/Term Paper/Term Paper.md",
    "MS2/Term Paper",
    "MS2/Term Paper/Term Paper Edited.md",
    "README.md",
    "Dictionary.md",
    "Diane Enns.md",
    "MS1/slides/15thJan26.pdf",
    "MS2/Enns.pdf",
    "MS2/Slides/HannahArendtLectureIdeologyTerror.pdf",
    "MS1/Midsem1 TODO.md"
  ]
}